{
 "姜子牙": [
  "姜子牙在磻溪垂釣渭水，日誦黃庭，悟道修真。",
  "姜子牙作詩感嘆自別崑崙二四年，期盼逢真主。",
  "姜子牙與樵子武吉對話，自稱道號飛熊。",
  "姜子牙指出武吉左眼青右眼紅，預言他今日進城會打死人。",
  "姜子牙表明自己直鉤垂釣，意在釣王與侯而非魚。"
 ],
 "姬昌": [
  "姬昌出示告示在西岐各門，宣布欲造靈臺以占風候看驗民災。",
  "姬昌每日給工銀一錢支用，並允許軍民隨願做工。",
  "姬昌傳旨給散銀兩，讓眾民領訖後選吉日破土興工。",
  "姬昌與文武多官排鑾輿出郭觀看工完的靈臺。",
  "姬昌因靈臺下欠少池沼以應水火既濟之意而鬱鬱不樂。",
  "姬昌傳旨讓散宜生再開一沼池以應水火既濟之意。",
  "姬昌命人將挖出的枯骨取來，用匣盛之埋於高阜之地。",
  "姬昌與文武在靈臺上設宴，君臣共樂。",
  "姬昌在靈臺上設繡榻而寢，三更時夢見東南白額猛虎脅生雙翼撲來。",
  "姬昌驚醒後自思此夢主何凶吉，待天明商議。",
  "姬昌召見散宜生詢問飛熊入夢的吉凶。",
  "姬昌聽散宜生解釋後，傳旨回駕並心欲訪賢以應此兆。",
  "姬昌駕臨靈臺時，門軍王相被武吉誤傷致死。",
  "姬昌在南門畫地為牢，將武吉禁於此間。",
  "姬昌准許散宜生之議，放武吉回家辦理事宜。"
 ],
 "散宜生": [
  "散宜生知民心歡悅，抱本進內啟奏文王。",
  "散宜生建議文王選吉日破土興工。",
  "散宜生見文王不悅，出班奏問原因。",
  "散宜生建議在靈臺下開一沼池以應水火既濟之意。",
  "散宜生忙傳王旨讓眾民開挖沼池。",
  "散宜生在南門過時，見武吉悲聲大哭並詢問原因。",
  "散宜生向文王啟奏，建議放武吉歸家辦養母之費及棺木衣衾之資。",
  "散宜生認為武吉打死王相實乃誤傷，自無抵償之理。"
 ],
 "武吉": [
  "武吉在磻溪邊唱歌並與姜子牙對話。",
  "武吉因姜子牙道號飛熊而揚笑不止。",
  "武吉建議姜子牙將釣針燒紅打成鉤樣並用香餌捕魚。",
  "武吉嘲笑姜子牙嘴臉不像王侯，像個活猴。",
  "武吉挑著一擔柴往西岐城中來賣。",
  "武吉在南門因道路窄狹換肩時，尖擔塌下打死門軍王相。",
  "武吉被拿住後見文王，自陳是西岐良民，因閃躲車駕誤傷王相。",
  "武吉被禁於南門畫地為牢中三日。",
  "武吉因思念七十餘歲無依無靠的老母而放聲大哭。",
  "武吉向散宜生哭訴自己無兄無弟無妻室，母親必成溝渠餓殍。",
  "武吉叩頭感謝散宜生的大恩。",
  "武吉出了獄後飛奔回家見母親。",
  "武吉哭拜在地，告知母親自己打死王相被禁，多虧散宜生啟奏文王放他歸家。",
  "武吉告知母親姜子牙預言他打死人的事。",
  "武吉收拾逕往磻溪來見姜子牙求救。"
 ],
 "馬氏": [
  "姜子牙棄卻朝歌並別了馬氏。"
 ]
}